pygsfit_cp/__init__.py
pygsfit_cp/ndfits.py
pygsfit_cp/pygsfit_cp.py
pygsfit_cp/pygsfit_cp_src.py
pygsfit_cp/pygsfit_cp_utils.py
pygsfit_cp/results_convertor.py
pygsfit_cp/IDL_utils/process_params_maps.pro
pygsfit_cp/IDL_utils/read_hdf5.pro
pygsfit_cp/IDL_utils/save_to_idl.pro
pygsfit_cp/IDL_utils/struct_delete_field.pro
pygsfit_cp/IDL_utils/test.pro
pygsfit_cp/demo/batch_mode_script.py
pygsfit_cp/demo/eovsa_allbd_demo_0.fits
pygsfit_cp/demo/eovsa_allbd_demo_1.fits
pygsfit_cp/demo/pygsfit_cp_Tutorial.ipynb
pygsfit_cp/docs/Long_input.txt
pygsfit_cp/docs/Parms_input.txt
pygsfit_cp/docs/Real_input.txt
pygsfit_cp/linux/fit_Spectrum_Kl.so
pygsfit_cp/unix/arm64/fit_Spectrum_Kl.so
pygsfit_cp/unix/arm64/fit_Spectrum_Kl_verb.so
pygsfit_cp/unix/x86/fit_Spectrum_Kl.so
pygsfit_cp/win/gs_fit_1D.dll
pygsfit_cp-0.1.4.dist-info/LICENSE
pygsfit_cp-0.1.4.dist-info/METADATA
pygsfit_cp-0.1.4.dist-info/WHEEL
pygsfit_cp-0.1.4.dist-info/top_level.txt
pygsfit_cp-0.1.4.dist-info/RECORD
